{"company": "\u676d\u5dde\u5065\u57f9\u79d1\u6280\u6709\u9650\u516c\u53f8", "position": "python\u5f00\u53d1\u5de5\u7a0b\u5e08", "salary": "6k-10k", "city": "\u676d\u5dde"}{"company": "\u5317\u4eac\u70b9\u77f3\u7ecf\u7eac\u79d1\u6280\u6709\u9650\u516c\u53f8", "position": "Python\u5de5\u7a0b\u5e08", "salary": "10k-20k", "city": "\u5317\u4eac"}{"company": "\u77ac\u8054\u8f6f\u4ef6\u79d1\u6280\uff08\u5317\u4eac\uff09\u6709\u9650\u516c\u53f8", "position": "python\u5f00\u53d1\u5de5\u7a0b\u5e08", "salary": "10k-15k", "city": "\u4e0a\u6d77"}{"company": "\u5317\u4eac\u535a\u6d3e\u901a\u8fbe\u79d1\u6280\u6709\u9650\u516c\u53f8", "position": "Python", "salary": "10K-20K", "city": "\u5317\u4eac"}{"company": "\u6b66\u6c49\u6781\u610f\u7f51\u7edc\u79d1\u6280\u6709\u9650\u516c\u53f8", "position": "Python\u5de5\u7a0b\u5e08", "salary": "8k-10k", "city": "\u6b66\u6c49"}{"company": "\u6b66\u6c49\u5353\u7ff0\u7f51\u7edc\u79d1\u6280\u6709\u9650\u516c\u53f8", "position": "Python\u7814\u53d1\u5de5\u7a0b\u5e08", "salary": "15k-25k", "city": "\u6b66\u6c49"}{"company": "\u6df1\u5733\u4f17\u7984\u91d1\u878d\u63a7\u80a1\u80a1\u4efd\u6709\u9650\u516c\u53f8", "position": "python\u5de5\u7a0b\u5e08", "salary": "18k-25k", "city": "\u6df1\u5733"}{"company": "\u5317\u4eac\u4e91\u65cf\u4f73\u79d1\u6280\u6709\u9650\u516c\u53f8", "position": "python\u5f00\u53d1-\u90d1\u5dde", "salary": "20k-25k", "city": "\u90d1\u5dde"}{"company": "\u90d1\u5dde\u521b\u6052\u5b9e\u4e1a\u6709\u9650\u516c\u53f8", "position": "Python\u5f00\u53d1\u5de5\u7a0b\u5e08", "salary": "5k-10k", "city": "\u90d1\u5dde"}{"company": "\u5e7f\u5dde\u7b77\u5b50\u4fe1\u606f\u79d1\u6280\u6709\u9650\u516c\u53f8", "position": "python\u5de5\u7a0b\u5e08", "salary": "10k-15k", "city": "\u5e7f\u5dde"}{"company": "\u4e0a\u6d77\u5e1d\u8054\u4fe1\u606f\u79d1\u6280\u80a1\u4efd\u6709\u9650\u516c\u53f8", "position": "python\u7814\u53d1\u5de5\u7a0b\u5e08", "salary": "6k-9k", "city": "\u5357\u901a"}{"company": "\u6df1\u5733\u5e02\u535a\u96c5\u6210\u4fe1\u91d1\u878d\u670d\u52a1\u6709\u9650\u516c\u53f8", "position": "Python\u5f00\u53d1\u5de5\u7a0b\u5e08", "salary": "8k-15k", "city": "\u6210\u90fd"}{"company": "\u7ef4\u6211\u8f6f\u4ef6\uff08\u4e0a\u6d77\uff09\u6709\u9650\u516c\u53f8\u5317\u4eac\u5206\u516c\u53f8", "position": "Python\u8f6f\u4ef6\u5f00\u53d1\u5de5\u7a0b\u5e08", "salary": "15k-25k", "city": "\u5317\u4eac"}{"company": "\u518d\u60e0\uff08\u4e0a\u6d77\uff09\u7f51\u7edc\u79d1\u6280\u6709\u9650\u516c\u53f8", "position": "Python\u5f00\u53d1\u5de5\u7a0b\u5e08", "salary": "15k-30k", "city": "\u4e0a\u6d77"}{"company": "\u4e0a\u6d77\u54c8\u675c\u79d1\u6280\u6709\u9650\u516c\u53f8", "position": "Python", "salary": "15k-25k", "city": "\u4e0a\u6d77"}{"company": "\u5317\u4eac\u4e91\u65cf\u4f73\u79d1\u6280\u6709\u9650\u516c\u53f8", "position": "python\u5f00\u53d1-\u6b66\u6c49", "salary": "20k-25k", "city": "\u6b66\u6c49"}{"company": "\u7ef4\u6211\u8f6f\u4ef6\uff08\u4e0a\u6d77\uff09\u6709\u9650\u516c\u53f8\u5317\u4eac\u5206\u516c\u53f8", "position": "Python", "salary": "25k-35k", "city": "\u5317\u4eac"}{"company": "\u676d\u5dde\u7fa4\u6838\u4fe1\u606f\u6280\u672f\u6709\u9650\u516c\u53f8", "position": "Python\u7814\u53d1\u5de5\u7a0b\u5e08", "salary": "15k-23k", "city": "\u676d\u5dde"}{"company": "\u4e0a\u6d77\u4f17\u8a00\u7f51\u7edc\u79d1\u6280\u6709\u9650\u516c\u53f8", "position": "Python\u5de5\u7a0b\u5e08", "salary": "15k-25k", "city": "\u82cf\u5dde"}{"company": "\u540c\u6e90\u6570\u667a\uff08\u5317\u4eac\uff09\u79d1\u6280\u6709\u9650\u516c\u53f8", "position": "Python\u5f00\u53d1\u5de5\u7a0b\u5e08", "salary": "10k-20k", "city": "\u5317\u4eac"}{"company": "\u4e0a\u6d77\u732b\u7a7a\u4fe1\u606f\u6280\u672f\u6709\u9650\u516c\u53f8", "position": "Python", "salary": "10k-15k", "city": "\u4e0a\u6d77"}{"company": "\u8389\u8389\u4e1d\u79d1\u6280\uff08\u4e0a\u6d77\uff09\u6709\u9650\u516c\u53f8", "position": "Python\u5f00\u53d1\u5de5\u7a0b\u5e08", "salary": "10k-20k", "city": "\u4e0a\u6d77"}{"company": "\u4e0a\u6d77\u822a\u4ed5\u4f01\u4e1a\u7ba1\u7406\u6709\u9650\u516c\u53f8", "position": "Python\u5f00\u53d1", "salary": "20k-35k", "city": "\u6df1\u5733"}{"company": "\u5317\u4eac\u65f7\u89c6\u79d1\u6280\u6709\u9650\u516c\u53f8", "position": "Python\u5de5\u7a0b\u5e08", "salary": "20k-40k", "city": "\u5317\u4eac"}{"company": "\u676d\u5dde\u4e00\u77e5\u667a\u80fd\u79d1\u6280\u6709\u9650\u516c\u53f8", "position": "python\u5de5\u7a0b\u5e08", "salary": "7K-12K", "city": "\u676d\u5dde"}{"company": "\u676d\u5dde\u7f8e\u767b\u79d1\u6280\u6709\u9650\u516c\u53f8", "position": "Python\u7814\u53d1\u5de5\u7a0b\u5e08", "salary": "15k-30k", "city": "\u676d\u5dde"}{"company": "\u65e0\u9521\u534e\u4e91\u6570\u636e\u6280\u672f\u670d\u52a1\u6709\u9650\u516c\u53f8", "position": "Python\u5f00\u53d1\u5de5\u7a0b\u5e08", "salary": "18k-28k", "city": "\u4e0a\u6d77"}{"company": "\u4e0a\u6d77\u9605\u6587\u4fe1\u606f\u6280\u672f\u6709\u9650\u516c\u53f8", "position": "Python\u5f00\u53d1\u5de5\u7a0b\u5e08", "salary": "15k-25k", "city": "\u4e0a\u6d77"}{"company": "\u4e0a\u6d77\u9752\u5ba2\u516c\u5171\u79df\u8d41\u4f4f\u623f\u79df\u8d41\u7ecf\u8425\u7ba1\u7406\u80a1\u4efd\u6709\u9650\u516c\u53f8", "position": "python\u5de5\u7a0b\u5e08", "salary": "15k-25k", "city": "\u4e0a\u6d77"}{"company": "\u5317\u4eac\u6c49\u8fea\u79fb\u52a8\u4e92\u8054\u7f51\u79d1\u6280\u80a1\u4efd\u6709\u9650\u516c\u53f8", "position": "Python\u5f00\u53d1\u5de5\u7a0b\u5e08", "salary": "15k-30k", "city": "\u5317\u4eac"}